{
  "project_info": {
    "project_number": "714103885883",
    "project_id": "gicaform-notifications",
    "storage_bucket": "gicaform-notifications.firebasestorage.app"
  },
  "client": [
    {
      "client_info": {
        "mobilesdk_app_id": "1:714103885883:android:2be2aeed747dbb1cf50c1e",
        "android_client_info": {
          "package_name": "com.example.gica2025"
        }
      },
      "oauth_client": [],
      "api_key": [
        {
          "current_key": "AIzaSyDY_ua3LMmlLtBjORFQiq_riZQMju-AFHg"
        }
      ],
      "services": {
        "appinvite_service": {
          "other_platform_oauth_client": []
        }
      }
    }
  ],
  "configuration_version": "1"
}